bsteno/__init__.py
bsteno/bsteno.py
bsteno/bsteno_extract.py
bsteno/bsteno_insert.py
bsteno-0.1.0.dist-info/entry_points.txt
bsteno-0.1.0.dist-info/LICENSE.md
bsteno-0.1.0.dist-info/WHEEL
bsteno-0.1.0.dist-info/METADATA
bsteno-0.1.0.dist-info/RECORD
