Metadata-Version: 2.1
Name: bsteno
Version: 0.1.0
Summary: A python steganography package to insert/extract binary data into/from PNG files
Home-page: https://bitbucket.org/lordblackthorn/bsteno/src
License: MIT
Author: Blackthorn
Author-email: sosaria@protonmail.com
Requires-Python: >=3.7
Classifier: License :: OSI Approved :: MIT License
Classifier: Programming Language :: Python :: 3
Classifier: Programming Language :: Python :: 3.10
Classifier: Programming Language :: Python :: 3.7
Classifier: Programming Language :: Python :: 3.8
Classifier: Programming Language :: Python :: 3.9
Requires-Dist: Pillow (>=9.1.0,<10.0.0)
Project-URL: Repository, https://bitbucket.org/lordblackthorn/bsteno/src
